rl_plotter/__init__.py
rl_plotter/log_utils.py
rl_plotter/logger.py
rl_plotter/plot_util.py
rl_plotter/plot_utils.py
rl_plotter/plotter.py
rl_plotter/plotter_spinup.py
rl_plotter-2.4.0.dist-info/LICENSE
rl_plotter-2.4.0.dist-info/METADATA
rl_plotter-2.4.0.dist-info/WHEEL
rl_plotter-2.4.0.dist-info/entry_points.txt
rl_plotter-2.4.0.dist-info/top_level.txt
rl_plotter-2.4.0.dist-info/RECORD
