Metadata-Version: 2.1
Name: rl-plotter
Version: 2.4.0
Summary: A plotter for reinforcement learning (RL)
Home-page: https://github.com/gxywy/rl-plotter
Author: Xiaoyu Gong
Author-email: gxywy@hotmail.com
License: UNKNOWN
Platform: UNKNOWN
Classifier: Programming Language :: Python :: 3
Classifier: License :: OSI Approved :: GNU General Public License v3 (GPLv3)
Classifier: Operating System :: OS Independent
Requires-Python: >=3.0
